{"v":4,"entries":{"test-from-inputs--test-form":{"id":"test-from-inputs--test-form","title":"Test From Inputs","name":"Test Form","importPath":"./src/app/test-form/test-form.component.stories.ts","tags":["story"],"type":"story"},"test-password-input--test-form":{"id":"test-password-input--test-form","title":"Test Password Input","name":"Test Form","importPath":"./src/app/test-form/test-password/test-password.component.stories.ts","tags":["story"],"type":"story"},"test-text-input--test-form":{"id":"test-text-input--test-form","title":"Test Text Input","name":"Test Form","importPath":"./src/app/test-form/text-input/text-input.component.stories.ts","tags":["story"],"type":"story"},"button--button":{"id":"button--button","title":"Button","name":"Button","importPath":"./src/stories/components/button/button.component.stories.ts","tags":["story"],"type":"story"}}}
